tp_timesheet/__init__.py
tp_timesheet/__main__.py
tp_timesheet/clockify_timesheet.py
tp_timesheet/config.py
tp_timesheet/date_utils.py
tp_timesheet/schedule.py
tp_timesheet-2.1.1.dist-info/LICENSE
tp_timesheet-2.1.1.dist-info/METADATA
tp_timesheet-2.1.1.dist-info/WHEEL
tp_timesheet-2.1.1.dist-info/entry_points.txt
tp_timesheet-2.1.1.dist-info/top_level.txt
tp_timesheet-2.1.1.dist-info/RECORD
