Metadata-Version: 2.1
Name: tp-timesheet
Version: 2.1.1
Summary: CLI tool to automate the submisison of tp timesheets
Home-page: https://github.com/ThorpeJosh/tp-timesheet
Author: Joshua Thorpe
Author-email: josh@thorpe.engineering
License: MIT
Keywords: automation,timesheet,cli,executable
Classifier: License :: OSI Approved :: MIT License
Classifier: Programming Language :: Python
Classifier: Programming Language :: Python :: 3
Classifier: Programming Language :: Python :: 3.6
Classifier: Programming Language :: Python :: 3.7
Classifier: Programming Language :: Python :: 3.8
Classifier: Programming Language :: Python :: 3.9
Classifier: Programming Language :: Python :: 3.10
Classifier: Operating System :: Microsoft :: Windows
Classifier: Operating System :: POSIX :: Linux
Classifier: Operating System :: MacOS
Requires-Python: >=3.8
License-File: LICENSE
Requires-Dist: croniter ~=1.3
Requires-Dist: python-crontab ~=2.6
Requires-Dist: python-dateutil ~=2.8
Requires-Dist: requests ~=2.0
Requires-Dist: workalendar ~=16.4.0
Provides-Extra: dev
Requires-Dist: pytest ==7.2.* ; extra == 'dev'
Requires-Dist: pylint ==2.16.* ; extra == 'dev'
Requires-Dist: black ==23.1.* ; extra == 'dev'
Requires-Dist: mock ==4.0.3 ; extra == 'dev'
